Conveyor/Pipeline.py
Conveyor/Stages.py
Conveyor/SyntaxAnalyzer.py
Conveyor/__init__.py
Pdp/PdpPipeline.py
Pdp/PdpStages.py
Pdp/PdpSyntaxAnalyzer.py
Pdp/__init__.py
conveyor/Pipeline.py
conveyor/Stages.py
conveyor/SyntaxAnalyzer.py
conveyor/__init__.py
conveyor/pipeline.py
conveyor/stages.py
conveyor/syntax_analyzer.py
tests/__init__.py
tests/test_pipeline_architecture.py
tests/test_pipeline_functionality.py
tests/test_pipes.py
tests/test_processors.py
parallel_conveyor-0.1.3.dist-info/LICENSE.txt
parallel_conveyor-0.1.3.dist-info/METADATA
parallel_conveyor-0.1.3.dist-info/WHEEL
parallel_conveyor-0.1.3.dist-info/top_level.txt
parallel_conveyor-0.1.3.dist-info/RECORD
