Metadata-Version: 2.1
Name: parallel-conveyor
Version: 0.1.3
Summary: Simple, intuitive pipelining in Python
Home-page: https://github.com/DanielKrolopp/Conveyor
Author: Conveyor Team
License: UNKNOWN
Platform: UNKNOWN
Classifier: Programming Language :: Python :: 3
Classifier: Operating System :: OS Independent
Requires-Python: >=3.8
